Workbook

Sheet Léeme
B2: Inventario del catálogo web · Talabartería Cartago
B3: Esta hoja alimenta la página web. Lo que cambien aquí aparece en el sitio en máximo 5 minutos.
B5: Pestañas
B6: Productos: una fila por producto (nombre, categoría, subcategoría, marca, descripción, precio).
B7: Variantes: una fila por cada color de cada producto, con su stock.
B8: Imagenes: una fila por foto de cada producto, en orden. La foto 1 es la portada.
B9: Marcas: las marcas que vende Cartago y el link de su logo (opcional).
B10: Configuracion: la tasa del dólar. Se actualiza cada 8 días.
B11: Listas: categorías y subcategorías permitidas.
B13: Cómo llenar
B14: 1. La fila 2 de cada pestaña (en rosado) es un ejemplo. Bórrenla cuando carguen el primer producto real: si no, aparece en la página.
B15: 2. Cada producto tiene un id corto y único: una letra y un número (m1, m2 para monturas; e1 para equino; j1 para jinete). Nunca reutilicen un id.
... B32: No cambien los nombres de las pestañas ni de los encabezados: la página los usa para leer los datos.

Sheet Productos
A1: id | B1: nombre | C1: categoria | D1: subcategoria | E1: marca | F1: descripcion | G1: precio | H1: precio_usd | I1: activo | J1: destacado | K1: personalizable | L1: nota_personalizacion | M1: garantia | N1: stock_total | O1: fotos
A2: e2 | B2: Freno a la medida | C2: Equino | D2: Cabeza | E2: Cartago | F2: Freno fabricado bajo medida para tu caballo. | G2: 0 | I2: SI | J2: SI | K2: NO | M2: Garantía de cambio: lo ensayas y, si no se le acomoda a tu caballo, te lo cambiamos sin costo adicional. | N2: =IF(A2="","",SUMIF(Variantes!A:A,A2,Variantes!D:D)) | O2: =IF(A2="","",COUNTIF(Imagenes!A:A,A2))
N3: =IF(A3="","",SUMIF(Variantes!A:A,A3,Variantes!D:D)) | O3: =IF(A3="","",COUNTIF(Imagenes!A:A,A3))
N4: =IF(A4="","",SUMIF(Variantes!A:A,A4,Variantes!D:D)) | O4: =IF(A4="","",COUNTIF(Imagenes!A:A,A4))
N5: =IF(A5="","",SUMIF(Variantes!A:A,A5,Variantes!D:D)) | O5: =IF(A5="","",COUNTIF(Imagenes!A:A,A5))
N6: =IF(A6="","",SUMIF(Variantes!A:A,A6,Variantes!D:D)) | O6: =IF(A6="","",COUNTIF(Imagenes!A:A,A6))
N7: =IF(A7="","",SUMIF(Variantes!A:A,A7,Variantes!D:D)) | O7: =IF(A7="","",COUNTIF(Imagenes!A:A,A7))
N8: =IF(A8="","",SUMIF(Variantes!A:A,A8,Variantes!D:D)) | O8: =IF(A8="","",COUNTIF(Imagenes!A:A,A8))
N9: =IF(A9="","",SUMIF(Variantes!A:A,A9,Variantes!D:D)) | O9: =IF(A9="","",COUNTIF(Imagenes!A:A,A9))
N10: =IF(A10="","",SUMIF(Variantes!A:A,A10,Variantes!D:D)) | O10: =IF(A10="","",COUNTIF(Imagenes!A:A,A10))
N11: =IF(A11="","",SUMIF(Variantes!A:A,A11,Variantes!D:D)) | O11: =IF(A11="","",COUNTIF(Imagenes!A:A,A11))
N12: =IF(A12="","",SUMIF(Variantes!A:A,A12,Variantes!D:D)) | O12: =IF(A12="","",COUNTIF(Imagenes!A:A,A12))
N13: =IF(A13="","",SUMIF(Variantes!A:A,A13,Variantes!D:D)) | O13: =IF(A13="","",COUNTIF(Imagenes!A:A,A13))
N14: =IF(A14="","",SUMIF(Variantes!A:A,A14,Variantes!D:D)) | O14: =IF(A14="","",COUNTIF(Imagenes!A:A,A14))
... N151: =IF(A151="","",SUMIF(Variantes!A:A,A151,Variantes!D:D)) | O151: =IF(A151="","",COUNTIF(Imagenes!A:A,A151))

Sheet Variantes
A1: producto_id | B1: sku | C1: color | D1: stock
A2: e2 | B2: e2 | D2: 10

Sheet Imagenes
A1: producto_id | B1: orden | C1: url | D1: archivo
A2: e2 | B2: 1 | C2: https://res.cloudinary.com/.../e2-1.jpg | D2: e2-1.jpg

Sheet Marcas
A1: marca | B1: logo_url
A2: Cartago
A3: San Fermín
A4: Mesacé
A5: Al Torno
A6: Sybec
A7: Natural V.
A8: Cheval

Sheet Configuracion
A1: clave | B1: valor | C1: descripcion
A2: tasa_usd | B2: 3000 | C2: Pesos por dólar para mostrar precios en USD. Se actualiza cada 8 días.

Sheet Listas
A1: categorias | C1: subcategorias | D1: de la categoría
A2: Monturas | C2: Sillas | D2: Monturas
A3: Equino | C3: Tereques | D3: Monturas
A4: Jinete | C4: Galápagos | D4: Monturas
A5: Cuidado del caballo | C5: Kids | D5: Monturas
A6: Caninos | C6: Cabeza | D6: Equino
C7: Alfombras | D7: Equino
C8: Alforjas | D8: Equino
C9: Correaje | D9: Equino
C10: Tarabas | D10: Equino
C11: Sombreros | D11: Jinete
C12: Marroquinería | D12: Jinete
C13: Bisutería | D13: Jinete
C14: Aseo | D14: Cuidado del caballo
C15: Suplementos | D15: Cuidado del caballo
C16: Accesorios | D16: Cuidado del caballo
C17: Pecheras | D17: Caninos
C18: Collares | D18: Caninos
... C20: Bozales | D20: Caninos
